{
  "timestamp": "2025-11-12T11:12:12Z",
  "metrics": {
    "total_handovers": {"status":"success","data":{"resultType":"vector","result":[{"metric":{},"value":[1762945932.694,"7"]}]}}
,
    "failed_handovers": {"status":"success","data":{"resultType":"vector","result":[]}}
,
    "ml_fallbacks": {"status":"success","data":{"resultType":"vector","result":[{"metric":{},"value":[1762945932.782,"0"]}]}}
,
    "pingpong_suppressions": {"status":"success","data":{"resultType":"vector","result":[]}}
,
    "pingpong_too_recent": {"status":"success","data":{"resultType":"vector","result":[]}}
,
    "pingpong_too_many": {"status":"success","data":{"resultType":"vector","result":[]}}
,
    "pingpong_immediate": {"status":"success","data":{"resultType":"vector","result":[]}}
,
    "qos_compliance_ok": {"status":"success","data":{"resultType":"vector","result":[{"metric":{},"value":[1762945932.979,"525"]}]}}
,
    "qos_compliance_failed": {"status":"success","data":{"resultType":"vector","result":[]}}
,
    "qos_compliance_by_service": {"status":"success","data":{"resultType":"vector","result":[{"metric":{"service_type":"default"},"value":[1762945933.056,"199"]}]}}
,
    "qos_failures_by_service": {"status":"success","data":{"resultType":"vector","result":[]}}
,
    "qos_violations_by_metric": {"status":"success","data":{"resultType":"vector","result":[]}}
,
    "adaptive_confidence": {"status":"success","data":{"resultType":"vector","result":[{"metric":{"__name__":"ml_qos_adaptive_confidence","instance":"ml-service:5050","job":"ml_service","service_type":"default"},"value":[1762945933.181,"0.6799999999999999"]}]}}
,
    "total_predictions": {"status":"success","data":{"resultType":"vector","result":[{"metric":{},"value":[1762945933.219,"210"]}]}}
,
    "avg_confidence": {"status":"success","data":{"resultType":"vector","result":[{"metric":{},"value":[1762945933.264,"0.8772219459540387"]}]}}
,
    "p95_latency_ms": {"status":"success","data":{"resultType":"vector","result":[{"metric":{"instance":"ml-service:5050","job":"ml_service"},"value":[1762945933.309,"NaN"]}]}}
,
    "p50_handover_interval": {"status":"success","data":{"resultType":"vector","result":[{"metric":{"instance":"ml-service:5050","job":"ml_service"},"value":[1762945933.357,"NaN"]}]}}
,
    "p95_handover_interval": {"status":"success","data":{"resultType":"vector","result":[{"metric":{"instance":"ml-service:5050","job":"ml_service"},"value":[1762945933.403,"NaN"]}]}}

  }
}
